{
    "anims": [
        {
            "key": "bonfire_lit",
            "type": "frames",
            "repeat": -1,
            "frameRate": 12,
            "frames": [
                {
                    "key": "bonfire",
                    "frame": "bonfire0"
                },
                {
                    "key": "bonfire",
                    "frame": "bonfire1"
                },
                {
                    "key": "bonfire",
                    "frame": "bonfire2"
                },
                {
                    "key": "bonfire",
                    "frame": "bonfire3"
                },
                {
                    "key": "bonfire",
                    "frame": "bonfire4"
                },
                {
                    "key": "bonfire",
                    "frame": "bonfire5"
                },
                {
                    "key": "bonfire",
                    "frame": "bonfire6"
                },
                {
                    "key": "bonfire",
                    "frame": "bonfire7"
                },
                {
                    "key": "bonfire",
                    "frame": "bonfire8"
                }
            ]
        }
    ]
}